Changes
LICENSE
MANIFEST.in
setup.py
termcast_server/__init__.py
termcast_server/__main__.py
termcast_server/index.html
termcast_server/pubsub.py
termcast_server/ssh.py
termcast_server/termcast.py
termcast_server/web.py
termcast_server.egg-info/PKG-INFO
termcast_server.egg-info/SOURCES.txt
termcast_server.egg-info/dependency_links.txt
termcast_server.egg-info/entry_points.txt
termcast_server.egg-info/requires.txt
termcast_server.egg-info/top_level.txt