Metadata-Version: 1.1
Name: termcast-server
Version: 0.1.1
Summary: allow users to broadcast their terminals for others to watch
Home-page: https://github.com/doy/python-termcast-server
Author: Jesse Luehrs
Author-email: doy@tozt.net
License: MIT
Platform: UNKNOWN
Classifier: Development Status :: 3 - Alpha
Classifier: Environment :: Console
Classifier: License :: OSI Approved :: MIT License
Classifier: Topic :: Terminals :: Terminal Emulators/X Terminals
